{"docs":[{"title":"We read the paper that forced Timnit Gebru out of Google. Here\u2019s what it says _ MIT Technology Review","priority":0},{"title":"The two-year fight to stop Amazon from selling face recognition to the police _ MIT Technology Review","priority":1},{"title":"Training a single AI model can emit as much carbon as five cars in their lifetimes - MIT Technology Review","priority":0},{"title":"A college kid created a fake, AI-generated blog. It reached #1 on Hacker News. _ MIT Technology Review","priority":0}],"keywords":["Machine Learning","Issues","Bias, Discrimination","Gender Bias","Gender Shades","Carbon Footprint, Sustainability, Green Computing","AI","Misuse","Fake Blog"]}